ZLLRP/__init__.py
ZLLRP/compat.py
ZLLRP/zllrp_func.py
ZLLRP/zllrp_prot_lib.py
ZLLRP/zllrp_xml_to_json.py
ZLLRP-0.0.5.dist-info/METADATA
ZLLRP-0.0.5.dist-info/WHEEL
ZLLRP-0.0.5.dist-info/top_level.txt
ZLLRP-0.0.5.dist-info/RECORD
