Metadata-Version: 2.1
Name: ZLLRP
Version: 0.0.5
Summary: ZLLRP Protocol
Home-page: http://www.tjzit.com/
Author: Liugang
Author-email: liugang@gosusncn.com
Maintainer: Liugang
Maintainer-email: liugang@gosusncn.com
License: GNU General Public License
Platform: UNKNOWN
Classifier: Programming Language :: Python
Classifier: Programming Language :: Python :: Implementation
Classifier: Programming Language :: Python :: 2.7
Classifier: Programming Language :: Python :: 3.6
Classifier: Programming Language :: Python :: 3.7
